arabica/__init__.py
arabica/arabica_freq.py
arabica/cappuccino.py
arabica/clean_ngram.py
arabica/clean_numbers.py
arabica/coffee_break.py
arabica/group.py
arabica/preprocess.py
arabica/sentiment.py
arabica/stopwords.py
arabica-1.8.2.dist-info/LICENSE
arabica-1.8.2.dist-info/METADATA
arabica-1.8.2.dist-info/WHEEL
arabica-1.8.2.dist-info/top_level.txt
arabica-1.8.2.dist-info/RECORD
