Metadata-Version: 2.1
Name: arabica
Version: 1.8.2
Summary: Python package for text mining of time-series data
Home-page: https://github.com/PetrKorab/Arabica
Author: Petr Koráb
Author-email: xpetrkorab@gmail.com
License: OSI Approved :: Apache Software License
Requires-Python: >=3.8, <3.11
License-File: LICENSE
Requires-Dist: pandas==1.4.0
Requires-Dist: numpy==1.22.1
Requires-Dist: nltk==3.6.2
Requires-Dist: regex==2022.10.31
Requires-Dist: finvader==1.0.4
Requires-Dist: matplotlib==3.6.0
Requires-Dist: matplotlib-inline==0.1.6
Requires-Dist: plotnine==0.10.1
Requires-Dist: wordcloud==1.9.3
Requires-Dist: jenkspy==0.3.2
Requires-Dist: vaderSentiment==3.3.2
Requires-Dist: cleantext==1.1.4
Requires-Dist: mizani==0.9.2
Requires-Dist: pillow==9.4.0
Requires-Dist: ftfy==6.2.0
Requires-Dist: chardet==5.2.0
